{"_id": {"$oid": "56664a26e4b05f769b0ffe82"}, "conceptDetailInfo": {"preferredTerm": "Asco (Group of artists)", "onHold": false, "conceptLevel": "LOCAL", "statusText": "Provisional", "levelId": 1, "userName": "qac001@artstor.org", "instituteId": 10327, "displayText": "Asco (Group of artists)  [9000432188] - Cornell", "stateId": 5, "modifiedUserADLId": 429348, "terms": {"term": [{"_id": 1506719, "termSource": [{"_id": "12438646", "preferred": true, "name": "NO SOURCE"}], "displayTerm": false, "preferred": true, "name": "Asco (Group of artists)"}], "count": 1}, "modifiedUserName": "qac001@artstor.org", "displayInstituteName": "Cornell", "recordType": "PERSON", "modifiedUserDisplayName": "qac001@artstor.org", "userADLId": 429348, "stateText": "NEW", "modifiedOn": "2015/12/07 22:10:30", "statusId": 1, "conceptId": 9000432188, "createdOn": "2015/12/07 22:10:30"}, "_class": "org.artstor.vw.name.service.data.ConceptDetail"}