{"_id": {"$oid": "5666addee4b05f769b1aaf46"}, "conceptDetailInfo": {"preferredTerm": "Vignola, Giacomo Barozzi da, Attributed to", "onHold": false, "conceptLevel": "LOCAL", "statusText": "Provisional", "levelId": 1, "userName": "qac001@artstor.org", "instituteId": 10327, "displayText": "Vignola, Giacomo Barozzi da, Attributed to  [9000437076] - Cornell", "stateId": 5, "modifiedUserADLId": 429348, "terms": {"term": [{"_id": 1514449, "termSource": [{"_id": "12438646", "preferred": true, "name": "NO SOURCE"}], "displayTerm": false, "preferred": true, "name": "Vignola, Giacomo Barozzi da, Attributed to"}], "count": 1}, "modifiedUserName": "qac001@artstor.org", "displayInstituteName": "Cornell", "recordType": "PERSON", "modifiedUserDisplayName": "qac001@artstor.org", "userADLId": 429348, "stateText": "NEW", "modifiedOn": "2015/12/08 5:15:58", "statusId": 1, "conceptId": 9000437076, "createdOn": "2015/12/08 5:15:58"}, "_class": "org.artstor.vw.name.service.data.ConceptDetail"}