{"_id": {"$oid": "56665984e4b05f769b1280bb"}, "conceptDetailInfo": {"onHold": false, "levelId": 1, "userName": "qac001@artstor.org", "displayText": "Shaw, John  [9000433788] - Cornell", "stateId": 5, "modifiedUserADLId": 429348, "notes": {"count": 1, "note": [{"typeId": "12438709", "noteText": "Artisan who was active from about 1768 to about 1816.", "typeName": "Scope notes"}]}, "modifiedUserDisplayName": "qac001@artstor.org", "userADLId": 429348, "legacyId": "PCNC10800", "conceptId": 9000433788, "preferredTerm": "Shaw, John", "statusId": 1, "terms": {"term": [{"_id": 1509308, "termSource": [{"_id": "12438646", "preferred": true, "name": "NO SOURCE"}], "displayTerm": false, "preferred": true, "name": "Shaw, John"}], "count": 1}, "conceptLevel": "LOCAL", "instituteId": 10327, "modifiedUserName": "qac001@artstor.org", "displayInstituteName": "Cornell", "recordType": "PERSON", "stateText": "NEW", "modifiedOn": "2015/12/07 23:16:04", "statusText": "Provisional", "createdOn": "2015/12/07 23:16:04"}, "_class": "org.artstor.vw.name.service.data.ConceptDetail"}