{"_id": {"$oid": "566647f2e4b05f769b0fac89"}, "conceptDetailInfo": {"preferredTerm": "Vibia Sabina, ca. 88-ca. 137", "onHold": false, "conceptLevel": "LOCAL", "statusText": "Provisional", "levelId": 1, "userName": "qac001@artstor.org", "instituteId": 10327, "displayText": "Vibia Sabina, ca. 88-ca. 137  [9000431886] - Cornell", "stateId": 5, "modifiedUserADLId": 429348, "terms": {"term": [{"_id": 1506229, "termSource": [{"_id": "12438646", "preferred": true, "name": "NO SOURCE"}], "displayTerm": false, "preferred": true, "name": "Vibia Sabina, ca. 88-ca. 137"}], "count": 1}, "modifiedUserName": "qac001@artstor.org", "displayInstituteName": "Cornell", "recordType": "PERSON", "modifiedUserDisplayName": "qac001@artstor.org", "userADLId": 429348, "stateText": "NEW", "modifiedOn": "2015/12/07 22:01:06", "statusId": 1, "conceptId": 9000431886, "createdOn": "2015/12/07 22:01:06"}, "_class": "org.artstor.vw.name.service.data.ConceptDetail"}