{"_id": {"$oid": "5666689ae4b05f769b15098d"}, "conceptDetailInfo": {"onHold": false, "levelId": 1, "userName": "qac001@artstor.org", "displayText": "Salas: Biblioteca Municipal; Palacio Valdes Salas  [9000434924] - Cornell", "stateId": 5, "modifiedUserADLId": 429348, "modifiedUserDisplayName": "qac001@artstor.org", "userADLId": 429348, "legacyId": "PCNR9185", "conceptId": 9000434924, "preferredTerm": "Salas: Biblioteca Municipal; Palacio Valdes Salas", "statusId": 1, "terms": {"term": [{"_id": 1511138, "termSource": [{"_id": "12438646", "preferred": true, "name": "NO SOURCE"}], "displayTerm": false, "preferred": true, "name": "Salas: Biblioteca Municipal; Palacio Valdes Salas"}], "count": 1}, "conceptLevel": "LOCAL", "instituteId": 10327, "modifiedUserName": "qac001@artstor.org", "displayInstituteName": "Cornell", "recordType": "CORPORATE BODY", "stateText": "NEW", "modifiedOn": "2015/12/08 0:20:26", "statusText": "Provisional", "createdOn": "2015/12/08 0:20:26"}, "_class": "org.artstor.vw.name.service.data.ConceptDetail"}