{"_id": {"$oid": "56664910e4b05f769b0fd576"}, "conceptDetailInfo": {"preferredTerm": "Tutankhamen, King of Egypt", "onHold": false, "conceptLevel": "LOCAL", "statusText": "Provisional", "levelId": 1, "userName": "qac001@artstor.org", "instituteId": 10327, "displayText": "Tutankhamen, King of Egypt  [9000432033] - Cornell", "stateId": 5, "modifiedUserADLId": 429348, "terms": {"term": [{"_id": 1506470, "termSource": [{"_id": "12438646", "preferred": true, "name": "NO SOURCE"}], "displayTerm": false, "preferred": true, "name": "Tutankhamen, King of Egypt"}], "count": 1}, "modifiedUserName": "qac001@artstor.org", "displayInstituteName": "Cornell", "recordType": "PERSON", "modifiedUserDisplayName": "qac001@artstor.org", "userADLId": 429348, "stateText": "NEW", "modifiedOn": "2015/12/07 22:05:52", "statusId": 1, "conceptId": 9000432033, "createdOn": "2015/12/07 22:05:52"}, "_class": "org.artstor.vw.name.service.data.ConceptDetail"}