{"_id": {"$oid": "56666c50e4b05f769b15ac11"}, "conceptDetailInfo": {"onHold": false, "levelId": 1, "userName": "qac001@artstor.org", "displayText": "Musee Granet  [9000435157] - Cornell", "stateId": 5, "modifiedUserADLId": 429348, "modifiedUserDisplayName": "qac001@artstor.org", "userADLId": 429348, "legacyId": "PCNR52", "conceptId": 9000435157, "preferredTerm": "Musee Granet", "statusText": "Provisional", "terms": {"term": [{"_id": 1511527, "termSource": [{"_id": "12438646", "preferred": true, "name": "NO SOURCE"}], "displayTerm": false, "preferred": true, "name": "Musee Granet"}, {"_id": 1511528, "termSource": [{"_id": "12438646", "preferred": true, "name": "NO SOURCE"}], "displayTerm": false, "preferred": false, "name": "Musee Granet des Beaux-Arts"}], "count": 2}, "events": {"count": 1, "event": [{"_id": "11315114", "placeName": "Aix-en-Provence, France", "name": "location", "locationMatched": false, "placeId": "4000024320"}]}, "conceptLevel": "LOCAL", "instituteId": 10327, "modifiedUserName": "qac001@artstor.org", "displayInstituteName": "Cornell", "recordType": "CORPORATE BODY", "stateText": "NEW", "modifiedOn": "2015/12/08 0:36:16", "statusId": 1, "createdOn": "2015/12/08 0:36:16"}, "_class": "org.artstor.vw.name.service.data.ConceptDetail"}