{"_id": {"$oid": "5666afbfe4b05f769b1af6d0"}, "conceptDetailInfo": {"preferredTerm": "Aspertini, Amico", "onHold": false, "conceptLevel": "LOCAL", "statusText": "Provisional", "levelId": 1, "userName": "qac001@artstor.org", "instituteId": 10327, "displayText": "Aspertini, Amico  [9000437227] - Cornell", "stateId": 5, "modifiedUserADLId": 429348, "terms": {"term": [{"_id": 1514653, "termSource": [{"_id": "12438646", "preferred": true, "name": "NO SOURCE"}], "displayTerm": false, "preferred": true, "name": "Aspertini, Amico"}], "count": 1}, "modifiedUserName": "qac001@artstor.org", "displayInstituteName": "Cornell", "recordType": "PERSON", "modifiedUserDisplayName": "qac001@artstor.org", "userADLId": 429348, "stateText": "NEW", "modifiedOn": "2015/12/08 5:23:59", "statusId": 1, "conceptId": 9000437227, "createdOn": "2015/12/08 5:23:59"}, "_class": "org.artstor.vw.name.service.data.ConceptDetail"}