{"_id": {"$oid": "56666123e4b05f769b13caa1"}, "conceptDetailInfo": {"onHold": false, "levelId": 1, "userName": "qac001@artstor.org", "displayText": "National Gallery of Victoria  [9000434401] - Cornell", "stateId": 5, "modifiedUserADLId": 429348, "modifiedUserDisplayName": "qac001@artstor.org", "userADLId": 429348, "legacyId": "PCNR3365", "conceptId": 9000434401, "preferredTerm": "National Gallery of Victoria", "statusText": "Provisional", "terms": {"term": [{"_id": 1510277, "termSource": [{"_id": "12438646", "preferred": true, "name": "NO SOURCE"}], "displayTerm": false, "preferred": true, "name": "National Gallery of Victoria"}], "count": 1}, "events": {"count": 1, "event": [{"_id": "11315114", "placeName": "Melbourne, Australia", "name": "location", "locationMatched": true, "placeId": "4000022794"}]}, "conceptLevel": "LOCAL", "instituteId": 10327, "modifiedUserName": "qac001@artstor.org", "displayInstituteName": "Cornell", "recordType": "CORPORATE BODY", "stateText": "NEW", "modifiedOn": "2015/12/07 23:48:35", "statusId": 1, "createdOn": "2015/12/07 23:48:35"}, "_class": "org.artstor.vw.name.service.data.ConceptDetail"}